copilotkit/__init__.py
copilotkit/action.py
copilotkit/agent.py
copilotkit/crewai/__init__.py
copilotkit/crewai/copilotkit_integration.py
copilotkit/crewai/crewai_agent.py
copilotkit/crewai/crewai_sdk.py
copilotkit/exc.py
copilotkit/html.py
copilotkit/integrations/__init__.py
copilotkit/integrations/fastapi.py
copilotkit/langchain.py
copilotkit/langgraph.py
copilotkit/langgraph_agent.py
copilotkit/langgraph_agui_agent.py
copilotkit/logging.py
copilotkit/parameter.py
copilotkit/protocol.py
copilotkit/runloop.py
copilotkit/sdk.py
copilotkit/types.py
copilotkit/utils.py
copilotkit-0.1.75.dist-info/METADATA
copilotkit-0.1.75.dist-info/WHEEL
copilotkit-0.1.75.dist-info/RECORD
