Metadata-Version: 2.3
Name: copilotkit
Version: 0.1.75
Summary: CopilotKit python SDK
License: MIT
Keywords: copilot,copilotkit,langgraph,langchain,ai,langsmith,langserve
Author: Markus Ecker
Author-email: markus.ecker@gmail.com
Requires-Python: >=3.10,<3.13
Classifier: License :: OSI Approved :: MIT License
Classifier: Programming Language :: Python :: 3
Classifier: Programming Language :: Python :: 3.10
Classifier: Programming Language :: Python :: 3.11
Classifier: Programming Language :: Python :: 3.12
Provides-Extra: crewai
Requires-Dist: ag-ui-langgraph[fastapi] (>=0.0.23)
Requires-Dist: crewai (==0.118.0) ; extra == "crewai"
Requires-Dist: fastapi (>=0.115.0,<0.116.0)
Requires-Dist: langchain (>=0.3.0)
Requires-Dist: langgraph (>=0.3.25,<1.1.0)
Requires-Dist: partialjson (>=0.0.8,<0.0.9)
Requires-Dist: toml (>=0.10.2,<0.11.0)
Project-URL: Homepage, https://copilotkit.ai
Project-URL: Repository, https://github.com/CopilotKit/CopilotKit/tree/main/sdk-python
